qgear/__init__.py
qgear/_modidx.py
qgear/cli.py
qgear/core.py
qgear/image.py
qgear/plotter.py
qgear/runner.py
qgear/data/alphabet_x32_y1.png
qgear/data/alphabet_x64_y16.png
qgear/data/cameraman_x256_y384.png
qgear/data/e_coli_bacteria_x192_y128.png
qgear/data/high-heels_x128_y128.png
qgear/data/high-heels_x32_y32.png
qgear/data/high-heels_x64_y64.png
qgear/data/igb_facade_x192_y128.png
qgear/data/micro_germ_x384_y256.png
qgear/data/xray-finger-8y_x64_y80.png
qgear/data/xray-foot-12y_x192_y128.png
qgear/data/xray-hand-4y_x128_y192.png
qgear/data/zebra_x192_y128.png
qgear/data/zebra_x384_y256.png
qgear/datacircuits/__init__.py
qgear/datacircuits/_util.py
qgear/datacircuits/_util_img.py
qgear/datacircuits/_version.py
qgear/datacircuits/frqi.py
qgear/datacircuits/neqr.py
qgear/datacircuits/qcrank.py
qgear/datacircuits/__pycache__/__init__.cpython-310.pyc
qgear/datacircuits/__pycache__/__init__.cpython-311.pyc
qgear/datacircuits/__pycache__/_util.cpython-310.pyc
qgear/datacircuits/__pycache__/_util.cpython-311.pyc
qgear/datacircuits/__pycache__/_util_img.cpython-310.pyc
qgear/datacircuits/__pycache__/_util_img.cpython-311.pyc
qgear/datacircuits/__pycache__/_version.cpython-310.pyc
qgear/datacircuits/__pycache__/_version.cpython-311.pyc
qgear/datacircuits/__pycache__/frqi.cpython-310.pyc
qgear/datacircuits/__pycache__/frqi.cpython-311.pyc
qgear/datacircuits/__pycache__/qcrank.cpython-310.pyc
qgear/datacircuits/__pycache__/qcrank.cpython-311.pyc
qgear/toolbox/PlotterBackbone.py
qgear/toolbox/PlotterQCrank.py
qgear/toolbox/Util_CudaQ.py
qgear/toolbox/Util_H5io4.py
qgear/toolbox/Util_IOfunc.py
qgear/toolbox/Util_Qiskit.py
qgear/toolbox/Util_ibm.py
qgear/toolbox/__init__.py
qgear/toolbox/__pycache__/PlotterBackbone.cpython-310.pyc
qgear/toolbox/__pycache__/PlotterBackbone.cpython-311.pyc
qgear/toolbox/__pycache__/PlotterQCrank.cpython-310.pyc
qgear/toolbox/__pycache__/PlotterQCrank.cpython-311.pyc
qgear/toolbox/__pycache__/Util_CudaQ.cpython-310.pyc
qgear-1.1.2.dist-info/LICENSE
qgear-1.1.2.dist-info/METADATA
qgear-1.1.2.dist-info/WHEEL
qgear-1.1.2.dist-info/entry_points.txt
qgear-1.1.2.dist-info/top_level.txt
qgear-1.1.2.dist-info/RECORD
