Metadata-Version: 2.1
Name: qgear
Version: 1.1.2
Summary: Q-Gear
Home-page: https://github.com/gzquse/qgear
Author: gzquse
Author-email: ziqinguse@gmail.com
License: Apache Software License 2.0
Keywords: nbdev jupyter notebook python
Platform: UNKNOWN
Classifier: Development Status :: 4 - Beta
Classifier: Intended Audience :: Developers
Classifier: Natural Language :: English
Classifier: Programming Language :: Python :: 3.10
Classifier: Programming Language :: Python :: 3.11
Classifier: Programming Language :: Python :: 3.12
Classifier: License :: OSI Approved :: Apache Software License
Requires-Python: >=3.10
License-File: LICENSE
Requires-Dist: cudaq
Requires-Dist: fastcore
Requires-Dist: ffsim
Requires-Dist: h5py
Requires-Dist: huggingface-hub
Requires-Dist: ipywidgets
Requires-Dist: joblib
Requires-Dist: matplotlib
Requires-Dist: numpy
Requires-Dist: omegaconf
Requires-Dist: open-clip-torch
Requires-Dist: pillow
Requires-Dist: pyfiglet
Requires-Dist: pylatexenc
Requires-Dist: pynvml
Requires-Dist: qiskit
Requires-Dist: qiskit-addon-sqd
Requires-Dist: qiskit-ibm-runtime
Requires-Dist: qiskit-aer
Requires-Dist: rich
Requires-Dist: safetensors
Requires-Dist: scipy
Requires-Dist: tensordict
Requires-Dist: torch
Requires-Dist: tqdm
Provides-Extra: dev
Requires-Dist: jupyterlab ; extra == 'dev'
Requires-Dist: nbdev ; extra == 'dev'
Requires-Dist: pennylane ; extra == 'dev'
